django_auto_one_to_one/__init__.py
django_auto_one_to_one/models.py
django_auto_one_to_one-3.3.6.dist-info/COPYING
django_auto_one_to_one-3.3.6.dist-info/METADATA
django_auto_one_to_one-3.3.6.dist-info/WHEEL
django_auto_one_to_one-3.3.6.dist-info/top_level.txt
django_auto_one_to_one-3.3.6.dist-info/RECORD
