Metadata-Version: 2.1
Name: django-auto-one-to-one
Version: 3.3.6
Summary: Automatically create and destroy child model instances
Home-page: https://chris-lamb.co.uk/projects/django-auto-one-to-one
Author: Chris Lamb
Author-email: chris@chris-lamb.co.uk
License-File: COPYING
Requires-Dist: Django>=1.11
